interactive_dtree/__init__.py
interactive_dtree/runner.py
interactive_dtree/app/__init__.py
interactive_dtree/app/tree_fitter.py
interactive_dtree/app/build/favicon.ico
interactive_dtree/app/build/index.html
interactive_dtree/app/build/logo192.png
interactive_dtree/app/build/logo512.png
interactive_dtree/app/build/robots.txt
interactive_dtree/app/build/static/css/main.c5202083.css
interactive_dtree/app/build/static/css/main.c5202083.css.map
interactive_dtree/app/build/static/js/453.f2b547d7.chunk.js
interactive_dtree/app/build/static/js/453.f2b547d7.chunk.js.map
interactive_dtree/app/build/static/js/main.14cc4ebb.js
interactive_dtree/app/build/static/js/main.14cc4ebb.js.LICENSE.txt
interactive_dtree/app/build/static/js/main.14cc4ebb.js.map
interactive_dtree-0.1.1.dist-info/METADATA
interactive_dtree-0.1.1.dist-info/WHEEL
interactive_dtree-0.1.1.dist-info/RECORD
